setup.py
src/theagao/__init__.py
src/theagao/to_extract_feature.py
src/theagao/to_plot.py
src/theagao.egg-info/PKG-INFO
src/theagao.egg-info/SOURCES.txt
src/theagao.egg-info/dependency_links.txt
src/theagao.egg-info/requires.txt
src/theagao.egg-info/top_level.txt