Metadata-Version: 1.1
Name: theagao
Version: 2019.4.19
Summary: this is the 1st version
Home-page: UNKNOWN
Author: theagao
Author-email: UNKNOWN
License: UNKNOWN
Platform: UNKNOWN
Classifier: Programming Language :: Python :: 2.7
